tg_server_bot/__init__.py
tg_server_bot/config-ex.ini
tg_server_bot/config.py
tg_server_bot/const.py
tg_server_bot/decorators.py
tg_server_bot/handlers.py
tg_server_bot/main.py
tg_server_bot/utils.py
tg_server_bot/verified_id-ex.txt
tg_server_bot-0.0.2.dist-info/METADATA
tg_server_bot-0.0.2.dist-info/WHEEL
tg_server_bot-0.0.2.dist-info/entry_points.txt
tg_server_bot-0.0.2.dist-info/top_level.txt
tg_server_bot-0.0.2.dist-info/RECORD
