Metadata-Version: 2.1
Name: tg-server-bot
Version: 0.0.2
Summary: A Telegram bot for Linux server management and shell execution.
Author: nobitaqaq
Classifier: Programming Language :: Python :: 3
Classifier: License :: OSI Approved :: MIT License
Classifier: Operating System :: POSIX :: Linux
Requires-Python: >=3.8
Requires-Dist: python-telegram-bot ==21.0.1
Requires-Dist: python-telegram-bot[socks] ==21.0.1
Requires-Dist: python-telegram-bot[ext] ==21.0.1
Requires-Dist: aiofiles ==23.1.0
Requires-Dist: aiohttp ==3.8.4
Requires-Dist: aiohttp-socks ==0.7.1
